ShynaTermux/ShynaTermuxSetup.py
ShynaTermux/Shyna_check_charge.py
ShynaTermux/Shyna_get_connection.py
ShynaTermux/Shyna_get_location.py
ShynaTermux/__init__.py
ShynaTermux-0.89.7.dist-info/LICENSE
ShynaTermux-0.89.7.dist-info/METADATA
ShynaTermux-0.89.7.dist-info/WHEEL
ShynaTermux-0.89.7.dist-info/top_level.txt
ShynaTermux-0.89.7.dist-info/RECORD
