Metadata-Version: 2.1
Name: ShynaTermux
Version: 0.89.7
Summary: Shyna Backend Functionality Package For Termux
Author: Shivam Sharma
Author-email: shivamsharma1913@gmail.com
License-File: LICENSE
Requires-Dist: ShynaTime
Requires-Dist: requests
Requires-Dist: setuptools
Requires-Dist: wheel
